[
  {
    "id": "a6261e01-302f-4e3f-8fb9-cb6a447c591a",
    "createdDate": "2021-02-05T10:03:19.817Z",
    "modifiedDate": "2021-02-05T10:03:19.817Z",
    "modifiedByUserName": "INTERNAL\\sa_repository",
    "customProperties": [],
    "owner": {
      "id": "044192a8-9ad4-442e-bbf7-dd6fa7079725",
      "userId": "sa_repository",
      "userDirectory": "INTERNAL",
      "name": "sa_repository",
      "privileges": null
    },
    "name": "QLogs",
    "connectionstring": "CUSTOM CONNECT TO \"provider=QvOdbcConnectorPackage.exe;driver=postgres;host=localhost;port=4432;db=QLogs;FetchTSWTZasTimestamp=1;MaxVarcharSize=262144;\"",
    "type": "QvOdbcConnectorPackage.exe",
    "engineObjectId": "a6261e01-302f-4e3f-8fb9-cb6a447c591a",
    "username": "qlogs_reader",
    "logOn": 0,
    "architecture": 0,
    "tags": [],
    "privileges": null,
    "schemaPath": "DataConnection"
  },
  {
    "id": "47a1cfd8-f70e-4a98-a00d-00fca6c8e253",
    "createdDate": "2021-02-05T10:03:19.888Z",
    "modifiedDate": "2021-02-05T10:03:19.888Z",
    "modifiedByUserName": "INTERNAL\\sa_repository",
    "customProperties": [],
    "owner": {
      "id": "044192a8-9ad4-442e-bbf7-dd6fa7079725",
      "userId": "sa_repository",
      "userDirectory": "INTERNAL",
      "name": "sa_repository",
      "privileges": null
    },
    "name": "AttachedFiles",
    "connectionstring": "\\\\DESKTOP-9CUUO63\\QlikSense\\StaticContent\\AppContent\\<APP_ID>",
    "type": "folder",
    "engineObjectId": "47a1cfd8-f70e-4a98-a00d-00fca6c8e253",
    "username": "",
    "logOn": 0,
    "architecture": 0,
    "tags": [],
    "privileges": null,
    "schemaPath": "DataConnection"
  },
  {
    "id": "82789c18-b81e-485d-899d-6ac314253059",
    "createdDate": "2021-02-05T10:03:20.586Z",
    "modifiedDate": "2021-02-05T10:03:20.586Z",
    "modifiedByUserName": "INTERNAL\\sa_repository",
    "customProperties": [],
    "owner": {
      "id": "044192a8-9ad4-442e-bbf7-dd6fa7079725",
      "userId": "sa_repository",
      "userDirectory": "INTERNAL",
      "name": "sa_repository",
      "privileges": null
    },
    "name": "monitor_apps_REST_app",
    "connectionstring": "CUSTOM CONNECT TO \"provider=QvRestConnector.exe;url=https://localhost/qrs/app/full;timeout=900;method=GET;autoDetectResponseType=true;keyGenerationStrategy=0;authSchema=ntlm;skipServerCertificateValidation=true;useCertificate=No;certificateStoreLocation=LocalMachine;certificateStoreName=My;trustedLocations=qrs-proxy%2https://localhost:4244;queryParameters=xrfkey%20000000000000000;addMissingQueryParametersToFinalRequest=false;queryHeaders=X-Qlik-XrfKey%20000000000000000%1User-Agent%2Windows;PaginationType=None;\"",
    "type": "QvRestConnector.exe",
    "engineObjectId": "82789c18-b81e-485d-899d-6ac314253059",
    "username": "DESKTOP-9CUUO63\\administrator",
    "logOn": 0,
    "architecture": 0,
    "tags": [],
    "privileges": null,
    "schemaPath": "DataConnection"
  },
  {
    "id": "3201a27b-802a-4a5e-ade5-bf36e07fcb3a",
    "createdDate": "2021-02-05T10:03:20.586Z",
    "modifiedDate": "2021-02-05T10:03:20.586Z",
    "modifiedByUserName": "INTERNAL\\sa_repository",
    "customProperties": [],
    "owner": {
      "id": "044192a8-9ad4-442e-bbf7-dd6fa7079725",
      "userId": "sa_repository",
      "userDirectory": "INTERNAL",
      "name": "sa_repository",
      "privileges": null
    },
    "name": "monitor_apps_REST_appobject",
    "connectionstring": "CUSTOM CONNECT TO \"provider=QvRestConnector.exe;url=https://localhost/qrs/app/object/full;timeout=900;method=GET;autoDetectResponseType=true;keyGenerationStrategy=0;authSchema=ntlm;skipServerCertificateValidation=true;useCertificate=No;certificateStoreLocation=LocalMachine;certificateStoreName=My;trustedLocations=qrs-proxy%2https://localhost:4244;queryParameters=xrfkey%20000000000000000;addMissingQueryParametersToFinalRequest=false;queryHeaders=X-Qlik-XrfKey%20000000000000000%1User-Agent%2Windows;PaginationType=None;\"",
    "type": "QvRestConnector.exe",
    "engineObjectId": "3201a27b-802a-4a5e-ade5-bf36e07fcb3a",
    "username": "DESKTOP-9CUUO63\\administrator",
    "logOn": 0,
    "architecture": 0,
    "tags": [],
    "privileges": null,
    "schemaPath": "DataConnection"
  },
  {
    "id": "06c3c2f6-7dc1-4e84-9ea6-0f15a67266de",
    "createdDate": "2021-02-05T10:03:20.586Z",
    "modifiedDate": "2021-02-05T10:03:20.586Z",
    "modifiedByUserName": "INTERNAL\\sa_repository",
    "customProperties": [],
    "owner": {
      "id": "044192a8-9ad4-442e-bbf7-dd6fa7079725",
      "userId": "sa_repository",
      "userDirectory": "INTERNAL",
      "name": "sa_repository",
      "privileges": null
    },
    "name": "monitor_apps_REST_event",
    "connectionstring": "CUSTOM CONNECT TO \"provider=QvRestConnector.exe;url=https://localhost/qrs/event/full;timeout=900;method=GET;autoDetectResponseType=true;keyGenerationStrategy=0;authSchema=ntlm;skipServerCertificateValidation=true;useCertificate=No;certificateStoreLocation=LocalMachine;certificateStoreName=My;trustedLocations=qrs-proxy%2https://localhost:4244;queryParameters=xrfkey%20000000000000000;addMissingQueryParametersToFinalRequest=false;queryHeaders=X-Qlik-XrfKey%20000000000000000%1User-Agent%2Windows;PaginationType=None;\"",
    "type": "QvRestConnector.exe",
    "engineObjectId": "06c3c2f6-7dc1-4e84-9ea6-0f15a67266de",
    "username": "DESKTOP-9CUUO63\\administrator",
    "logOn": 0,
    "architecture": 0,
    "tags": [],
    "privileges": null,
    "schemaPath": "DataConnection"
  },
  {
    "id": "c9c9659f-5f63-478c-b101-3f32c68ed35a",
    "createdDate": "2021-02-05T10:03:20.586Z",
    "modifiedDate": "2021-02-05T10:03:20.586Z",
    "modifiedByUserName": "INTERNAL\\sa_repository",
    "customProperties": [],
    "owner": {
      "id": "044192a8-9ad4-442e-bbf7-dd6fa7079725",
      "userId": "sa_repository",
      "userDirectory": "INTERNAL",
      "name": "sa_repository",
      "privileges": null
    },
    "name": "monitor_apps_REST_license_login",
    "connectionstring": "CUSTOM CONNECT TO \"provider=QvRestConnector.exe;url=https://localhost/qrs/license/loginaccesstype/full;timeout=900;method=GET;autoDetectResponseType=true;keyGenerationStrategy=0;authSchema=ntlm;skipServerCertificateValidation=true;useCertificate=No;certificateStoreLocation=LocalMachine;certificateStoreName=My;trustedLocations=qrs-proxy%2https://localhost:4244;queryParameters=xrfkey%20000000000000000;addMissingQueryParametersToFinalRequest=false;queryHeaders=X-Qlik-XrfKey%20000000000000000%1User-Agent%2Windows;PaginationType=None;\"",
    "type": "QvRestConnector.exe",
    "engineObjectId": "c9c9659f-5f63-478c-b101-3f32c68ed35a",
    "username": "DESKTOP-9CUUO63\\administrator",
    "logOn": 0,
    "architecture": 0,
    "tags": [],
    "privileges": null,
    "schemaPath": "DataConnection"
  },
  {
    "id": "089f7da4-4f46-4c1a-bbd1-ec61cf7bf07f",
    "createdDate": "2021-02-05T10:03:20.586Z",
    "modifiedDate": "2021-02-05T10:03:20.586Z",
    "modifiedByUserName": "INTERNAL\\sa_repository",
    "customProperties": [],
    "owner": {
      "id": "044192a8-9ad4-442e-bbf7-dd6fa7079725",
      "userId": "sa_repository",
      "userDirectory": "INTERNAL",
      "name": "sa_repository",
      "privileges": null
    },
    "name": "monitor_apps_REST_license_user",
    "connectionstring": "CUSTOM CONNECT TO \"provider=QvRestConnector.exe;url=https://localhost/qrs/license/useraccesstype/full;timeout=900;method=GET;autoDetectResponseType=true;keyGenerationStrategy=0;authSchema=ntlm;skipServerCertificateValidation=true;useCertificate=No;certificateStoreLocation=LocalMachine;certificateStoreName=My;trustedLocations=qrs-proxy%2https://localhost:4244;queryParameters=xrfkey%20000000000000000;addMissingQueryParametersToFinalRequest=false;queryHeaders=X-Qlik-XrfKey%20000000000000000%1User-Agent%2Windows;PaginationType=None;\"",
    "type": "QvRestConnector.exe",
    "engineObjectId": "089f7da4-4f46-4c1a-bbd1-ec61cf7bf07f",
    "username": "DESKTOP-9CUUO63\\administrator",
    "logOn": 0,
    "architecture": 0,
    "tags": [],
    "privileges": null,
    "schemaPath": "DataConnection"
  },
  {
    "id": "0cf9de8e-c340-491c-8a35-ec82683fad69",
    "createdDate": "2021-02-05T10:03:20.586Z",
    "modifiedDate": "2021-02-05T10:03:20.586Z",
    "modifiedByUserName": "INTERNAL\\sa_repository",
    "customProperties": [],
    "owner": {
      "id": "044192a8-9ad4-442e-bbf7-dd6fa7079725",
      "userId": "sa_repository",
      "userDirectory": "INTERNAL",
      "name": "sa_repository",
      "privileges": null
    },
    "name": "monitor_apps_REST_task",
    "connectionstring": "CUSTOM CONNECT TO \"provider=QvRestConnector.exe;url=https://localhost/qrs/task/full;timeout=900;method=GET;autoDetectResponseType=true;keyGenerationStrategy=0;authSchema=ntlm;skipServerCertificateValidation=true;useCertificate=No;certificateStoreLocation=LocalMachine;certificateStoreName=My;trustedLocations=qrs-proxy%2https://localhost:4244;queryParameters=xrfkey%20000000000000000;addMissingQueryParametersToFinalRequest=false;queryHeaders=X-Qlik-XrfKey%20000000000000000%1User-Agent%2Windows;PaginationType=None;\"",
    "type": "QvRestConnector.exe",
    "engineObjectId": "0cf9de8e-c340-491c-8a35-ec82683fad69",
    "username": "DESKTOP-9CUUO63\\administrator",
    "logOn": 0,
    "architecture": 0,
    "tags": [],
    "privileges": null,
    "schemaPath": "DataConnection"
  },
  {
    "id": "1d35a28f-3990-4753-a865-8329da82c228",
    "createdDate": "2021-02-05T10:03:20.586Z",
    "modifiedDate": "2021-02-05T10:03:20.586Z",
    "modifiedByUserName": "INTERNAL\\sa_repository",
    "customProperties": [],
    "owner": {
      "id": "044192a8-9ad4-442e-bbf7-dd6fa7079725",
      "userId": "sa_repository",
      "userDirectory": "INTERNAL",
      "name": "sa_repository",
      "privileges": null
    },
    "name": "monitor_apps_REST_user",
    "connectionstring": "CUSTOM CONNECT TO \"provider=QvRestConnector.exe;url=https://localhost/qrs/user/full;timeout=900;method=GET;autoDetectResponseType=true;keyGenerationStrategy=0;authSchema=ntlm;skipServerCertificateValidation=true;useCertificate=No;certificateStoreLocation=LocalMachine;certificateStoreName=My;trustedLocations=qrs-proxy%2https://localhost:4244;queryParameters=xrfkey%20000000000000000;addMissingQueryParametersToFinalRequest=false;queryHeaders=X-Qlik-XrfKey%20000000000000000%1User-Agent%2Windows;PaginationType=None;\"",
    "type": "QvRestConnector.exe",
    "engineObjectId": "1d35a28f-3990-4753-a865-8329da82c228",
    "username": "DESKTOP-9CUUO63\\administrator",
    "logOn": 0,
    "architecture": 0,
    "tags": [],
    "privileges": null,
    "schemaPath": "DataConnection"
  },
  {
    "id": "1058e05f-efbd-47d6-b0ab-c8e8b9aefc8e",
    "createdDate": "2021-02-05T10:03:20.586Z",
    "modifiedDate": "2021-02-05T10:03:20.586Z",
    "modifiedByUserName": "INTERNAL\\sa_repository",
    "customProperties": [],
    "owner": {
      "id": "044192a8-9ad4-442e-bbf7-dd6fa7079725",
      "userId": "sa_repository",
      "userDirectory": "INTERNAL",
      "name": "sa_repository",
      "privileges": null
    },
    "name": "monitor_apps_REST_user_condensed",
    "connectionstring": "CUSTOM CONNECT TO \"provider=QvRestConnector.exe;url=https://localhost/qrs/user;timeout=900;method=GET;autoDetectResponseType=true;keyGenerationStrategy=0;authSchema=ntlm;skipServerCertificateValidation=true;useCertificate=No;certificateStoreLocation=LocalMachine;certificateStoreName=My;trustedLocations=qrs-proxy%2https://localhost:4244;queryParameters=xrfkey%20000000000000000;addMissingQueryParametersToFinalRequest=false;queryHeaders=X-Qlik-XrfKey%20000000000000000%1User-Agent%2Windows;PaginationType=None;\"",
    "type": "QvRestConnector.exe",
    "engineObjectId": "1058e05f-efbd-47d6-b0ab-c8e8b9aefc8e",
    "username": "DESKTOP-9CUUO63\\administrator",
    "logOn": 0,
    "architecture": 0,
    "tags": [],
    "privileges": null,
    "schemaPath": "DataConnection"
  },
  {
    "id": "136bde2c-741d-4d36-bedf-9ca98d7080b9",
    "createdDate": "2021-02-05T10:03:20.586Z",
    "modifiedDate": "2021-02-05T10:03:20.586Z",
    "modifiedByUserName": "INTERNAL\\sa_repository",
    "customProperties": [],
    "owner": {
      "id": "044192a8-9ad4-442e-bbf7-dd6fa7079725",
      "userId": "sa_repository",
      "userDirectory": "INTERNAL",
      "name": "sa_repository",
      "privileges": null
    },
    "name": "monitor_apps_REST_license_overview",
    "connectionstring": "CUSTOM CONNECT TO \"provider=QvRestConnector.exe;url=https://localhost/qrs/license/accesstypeoverview;timeout=900;method=GET;autoDetectResponseType=true;keyGenerationStrategy=0;authSchema=ntlm;skipServerCertificateValidation=true;useCertificate=No;certificateStoreLocation=LocalMachine;certificateStoreName=My;trustedLocations=qrs-proxy%2https://localhost:4244;queryParameters=xrfkey%20000000000000000;addMissingQueryParametersToFinalRequest=false;queryHeaders=X-Qlik-XrfKey%20000000000000000%1User-Agent%2Windows;PaginationType=None;\"",
    "type": "QvRestConnector.exe",
    "engineObjectId": "136bde2c-741d-4d36-bedf-9ca98d7080b9",
    "username": "DESKTOP-9CUUO63\\administrator",
    "logOn": 0,
    "architecture": 0,
    "tags": [],
    "privileges": null,
    "schemaPath": "DataConnection"
  },
  {
    "id": "515e135f-6dec-425c-94df-cd38410c699c",
    "createdDate": "2021-02-05T10:03:20.586Z",
    "modifiedDate": "2021-02-05T10:03:20.586Z",
    "modifiedByUserName": "INTERNAL\\sa_repository",
    "customProperties": [],
    "owner": {
      "id": "044192a8-9ad4-442e-bbf7-dd6fa7079725",
      "userId": "sa_repository",
      "userDirectory": "INTERNAL",
      "name": "sa_repository",
      "privileges": null
    },
    "name": "monitor_apps_REST_license_professional",
    "connectionstring": "CUSTOM CONNECT TO \"provider=QvRestConnector.exe;url=https://localhost/qrs/license/professionalaccesstype/full;timeout=900;method=GET;autoDetectResponseType=true;keyGenerationStrategy=0;authSchema=ntlm;skipServerCertificateValidation=true;useCertificate=No;certificateStoreLocation=LocalMachine;certificateStoreName=My;trustedLocations=qrs-proxy%2https://localhost:4244;queryParameters=xrfkey%20000000000000000;addMissingQueryParametersToFinalRequest=false;queryHeaders=X-Qlik-XrfKey%20000000000000000%1User-Agent%2Windows;PaginationType=None;\"",
    "type": "QvRestConnector.exe",
    "engineObjectId": "515e135f-6dec-425c-94df-cd38410c699c",
    "username": "DESKTOP-9CUUO63\\administrator",
    "logOn": 0,
    "architecture": 0,
    "tags": [],
    "privileges": null,
    "schemaPath": "DataConnection"
  },
  {
    "id": "a10b8554-8858-4d3f-aece-9c881c1b94aa",
    "createdDate": "2021-02-05T10:03:20.586Z",
    "modifiedDate": "2021-02-05T10:03:20.586Z",
    "modifiedByUserName": "INTERNAL\\sa_repository",
    "customProperties": [],
    "owner": {
      "id": "044192a8-9ad4-442e-bbf7-dd6fa7079725",
      "userId": "sa_repository",
      "userDirectory": "INTERNAL",
      "name": "sa_repository",
      "privileges": null
    },
    "name": "monitor_apps_REST_license_analyzer",
    "connectionstring": "CUSTOM CONNECT TO \"provider=QvRestConnector.exe;url=https://localhost/qrs/license/analyzeraccesstype/full;timeout=900;method=GET;autoDetectResponseType=true;keyGenerationStrategy=0;authSchema=ntlm;skipServerCertificateValidation=true;useCertificate=No;certificateStoreLocation=LocalMachine;certificateStoreName=My;trustedLocations=qrs-proxy%2https://localhost:4244;queryParameters=xrfkey%20000000000000000;addMissingQueryParametersToFinalRequest=false;queryHeaders=X-Qlik-XrfKey%20000000000000000%1User-Agent%2Windows;PaginationType=None;\"",
    "type": "QvRestConnector.exe",
    "engineObjectId": "a10b8554-8858-4d3f-aece-9c881c1b94aa",
    "username": "DESKTOP-9CUUO63\\administrator",
    "logOn": 0,
    "architecture": 0,
    "tags": [],
    "privileges": null,
    "schemaPath": "DataConnection"
  },
  {
    "id": "425d5526-9fa8-4255-814b-2e4ee76c8b52",
    "createdDate": "2021-02-05T10:03:20.586Z",
    "modifiedDate": "2021-02-05T10:03:20.586Z",
    "modifiedByUserName": "INTERNAL\\sa_repository",
    "customProperties": [],
    "owner": {
      "id": "044192a8-9ad4-442e-bbf7-dd6fa7079725",
      "userId": "sa_repository",
      "userDirectory": "INTERNAL",
      "name": "sa_repository",
      "privileges": null
    },
    "name": "monitor_apps_REST_license",
    "connectionstring": "CUSTOM CONNECT TO \"provider=QvRestConnector.exe;url=https://localhost/qrs/license;timeout=900;method=GET;autoDetectResponseType=true;keyGenerationStrategy=0;authSchema=ntlm;skipServerCertificateValidation=true;useCertificate=No;certificateStoreLocation=LocalMachine;certificateStoreName=My;trustedLocations=qrs-proxy%2https://localhost:4244;queryParameters=xrfkey%20000000000000000;addMissingQueryParametersToFinalRequest=false;queryHeaders=X-Qlik-Xrfkey%20000000000000000%1User-Agent%2Windows;PaginationType=None;\"",
    "type": "QvRestConnector.exe",
    "engineObjectId": "425d5526-9fa8-4255-814b-2e4ee76c8b52",
    "username": "DESKTOP-9CUUO63\\administrator",
    "logOn": 0,
    "architecture": 0,
    "tags": [],
    "privileges": null,
    "schemaPath": "DataConnection"
  },
  {
    "id": "059b0778-1d27-4398-8973-300484554382",
    "createdDate": "2021-02-05T10:03:20.657Z",
    "modifiedDate": "2021-02-05T10:03:20.657Z",
    "modifiedByUserName": "INTERNAL\\sa_repository",
    "customProperties": [],
    "owner": {
      "id": "044192a8-9ad4-442e-bbf7-dd6fa7079725",
      "userId": "sa_repository",
      "userDirectory": "INTERNAL",
      "name": "sa_repository",
      "privileges": null
    },
    "name": "ArchivedLogsFolder",
    "connectionstring": "\\\\DESKTOP-9CUUO63\\QlikSense\\ArchivedLogs",
    "type": "folder",
    "engineObjectId": "059b0778-1d27-4398-8973-300484554382",
    "username": "",
    "logOn": 0,
    "architecture": 0,
    "tags": [],
    "privileges": null,
    "schemaPath": "DataConnection"
  },
  {
    "id": "112b1b00-3a0e-4347-99c8-614bb07581f6",
    "createdDate": "2021-02-09T11:30:26.353Z",
    "modifiedDate": "2021-02-09T11:30:26.353Z",
    "modifiedByUserName": "INTERNAL\\sa_repository",
    "customProperties": [],
    "owner": {
      "id": "044192a8-9ad4-442e-bbf7-dd6fa7079725",
      "userId": "sa_repository",
      "userDirectory": "INTERNAL",
      "name": "sa_repository",
      "privileges": null
    },
    "name": "ServerLogFolder",
    "connectionstring": "C:\\ProgramData\\Qlik\\Sense\\Log\\",
    "type": "folder",
    "engineObjectId": "112b1b00-3a0e-4347-99c8-614bb07581f6",
    "username": "",
    "logOn": 0,
    "architecture": 0,
    "tags": [],
    "privileges": null,
    "schemaPath": "DataConnection"
  },
  {
    "id": "1bbf71b1-08c7-4572-8275-e0bc4e35e020",
    "createdDate": "2021-02-09T11:30:26.353Z",
    "modifiedDate": "2021-02-09T11:30:26.353Z",
    "modifiedByUserName": "INTERNAL\\sa_repository",
    "customProperties": [],
    "owner": {
      "id": "044192a8-9ad4-442e-bbf7-dd6fa7079725",
      "userId": "sa_repository",
      "userDirectory": "INTERNAL",
      "name": "sa_repository",
      "privileges": null
    },
    "name": "monitor_apps_qlikview_logs",
    "connectionstring": "C:\\ProgramData\\QlikTech\\QlikViewServer\\",
    "type": "folder",
    "engineObjectId": "1bbf71b1-08c7-4572-8275-e0bc4e35e020",
    "username": "",
    "logOn": 0,
    "architecture": 0,
    "tags": [],
    "privileges": null,
    "schemaPath": "DataConnection"
  },
  {
    "id": "946497f9-eccf-4431-8dda-c66737a74885",
    "createdDate": "2021-02-09T13:05:50.514Z",
    "modifiedDate": "2021-02-09T13:05:51.108Z",
    "modifiedByUserName": "INTERNAL\\sa_api",
    "customProperties": [],
    "owner": {
      "id": "be71bbca-cd94-4991-992a-016bd6cbeed0",
      "userId": "sa_api",
      "userDirectory": "INTERNAL",
      "name": "sa_api",
      "privileges": null
    },
    "name": "DataPrepAppCache",
    "connectionstring": "\\\\DESKTOP-9CUUO63\\QlikSense\\Apps\\DataPrepAppCache\\<APP_ID>",
    "type": "folder",
    "engineObjectId": "946497f9-eccf-4431-8dda-c66737a74885",
    "username": "",
    "logOn": 0,
    "architecture": 0,
    "tags": [],
    "privileges": null,
    "schemaPath": "DataConnection"
  },
  {
    "id": "04dbbc7d-b33a-46d0-aece-a568070ae951",
    "createdDate": "2021-02-16T18:22:39.245Z",
    "modifiedDate": "2021-02-16T18:22:39.245Z",
    "modifiedByUserName": "GAIN-INSIGHTS\\aldrinr",
    "customProperties": [],
    "owner": {
      "id": "db397afe-44c5-408e-a4c0-63a2a8466714",
      "userId": "aldrinr",
      "userDirectory": "GAIN-INSIGHTS",
      "name": "aldrinr",
      "privileges": null
    },
    "name": "PostgreSQL_localhost (gain-insights_aldrinr)",
    "connectionstring": "CUSTOM CONNECT TO \"provider=QvOdbcConnectorPackage.exe;driver=postgres;host=localhost;port=5432;db=mis-automation;SSLMode=prefer;UseSystemTrustStore=false;ByteaAsLongVarBinary=0;TextAsLongVarchar=0;UseUnicode=1;FetchTSWTZasTimestamp=1;MaxVarcharSize=262144;UseDeclareFetch=1;Fetch=200;EnableTableTypes=1;MoneyAsDecimal=1;QueryTimeout=30;\"",
    "type": "QvOdbcConnectorPackage.exe",
    "engineObjectId": "04dbbc7d-b33a-46d0-aece-a568070ae951",
    "username": "postgres",
    "logOn": 0,
    "architecture": 0,
    "tags": [],
    "privileges": null,
    "schemaPath": "DataConnection"
  },
  {
    "id": "e6aeeaf5-8fae-4041-8d84-b9994a8cf732",
    "createdDate": "2021-02-17T07:18:55.106Z",
    "modifiedDate": "2021-02-17T07:18:55.106Z",
    "modifiedByUserName": "GAIN-INSIGHTS\\aldrinr",
    "customProperties": [],
    "owner": {
      "id": "db397afe-44c5-408e-a4c0-63a2a8466714",
      "userId": "aldrinr",
      "userDirectory": "GAIN-INSIGHTS",
      "name": "aldrinr",
      "privileges": null
    },
    "name": "MIS (gain-insights_aldrinr)",
    "connectionstring": "E:\\Work Files\\MIS Application\\",
    "type": "folder",
    "engineObjectId": "e6aeeaf5-8fae-4041-8d84-b9994a8cf732",
    "username": "",
    "logOn": 0,
    "architecture": 0,
    "tags": [],
    "privileges": null,
    "schemaPath": "DataConnection"
  }
]